dataset_mount/__init__.py
dataset_mount/mount.py
dataset_mount-2.0.dist-info/METADATA
dataset_mount-2.0.dist-info/WHEEL
dataset_mount-2.0.dist-info/top_level.txt
dataset_mount-2.0.dist-info/RECORD
