Metadata-Version: 2.1
Name: dataset-mount
Version: 2.0
Summary: databricks s3 mount with assumed role
Home-page: UNKNOWN
Author: BOS TEAM
Author-email: bos-tribe@ReedElsevier.com
License: UNKNOWN
Platform: UNKNOWN
